LICENSE
README.md
setup.py
package/__init__.py
package/macutil
package/modules/__init__.py
package/modules/brute.py
package/modules/general.py
package/modules/utility.py
utilmac.egg-info/PKG-INFO
utilmac.egg-info/SOURCES.txt
utilmac.egg-info/dependency_links.txt
utilmac.egg-info/top_level.txt