Metadata-Version: 2.1
Name: utilmac
Version: 0.1.11
Summary: MAC Address brute forcing tool, used to bypass MAC based filtering
Home-page: https://github.com/Laneden-Labs/macutil
Author: Darryl lane
Author-email: Darryllane101@gmail.com
License: LICENSE.txt
Platform: UNKNOWN
License-File: LICENSE
